zkeymap/__init__.py
zkeymap/keys.py
zkeymap/keys_la.py
zkeymap/lang.py
zkeymap/py.typed
zkeymap/api/__init__.py
zkeymap/demo/__init__.py
zkeymap/demo/splitkb.py
zkeymap/generators/__init__.py
zkeymap/generators/utils.py
zkeymap/generators/drawer/__init__.py
zkeymap/generators/drawer/private.py
zkeymap/generators/qmk/__init__.py
zkeymap/generators/qmk/private.py
zkeymap/generators/svg/__init__.py
zkeymap/generators/svg/private.py
zkeymap/generators/svg/themes.py
zkeymap/generators/zmk/__init__.py
zkeymap/generators/zmk/private.py
zkeymap/layouts/__init__.py
zkeymap/layouts/marz_split_3x6_4.py
zkeymap/layouts/utils.py
zkeymap/private/__init__.py
zkeymap/private/behavior.py
zkeymap/private/data.py
zkeymap/private/errors.py
zkeymap/private/grammars.py
zkeymap/private/keymap.py
zkeymap/private/lang.py
zkeymap/private/lark_utils.py
zkeymap/private/layout.py
zkeymap/private/oracle.py
zkeymap/private/parser.py
zkeymap/private/proxy.py
zkeymap/private/unicode.py
zkeymap/private/utils.py
zkeymap/tests/__init__.py
zkeymap/tests/test_grammar.py
zkeymap/tests/test_layout.py
zkeymap/tests/utils.py
zkeymap-0.1.12.dist-info/METADATA
zkeymap-0.1.12.dist-info/WHEEL
zkeymap-0.1.12.dist-info/licenses/LICENSE.md
zkeymap-0.1.12.dist-info/RECORD
