Metadata-Version: 2.4
Name: zkeymap
Version: 0.1.12
Summary: ZMK Keymap Generator
Project-URL: Homepage, https://github.com/mnesarco/zkeymap
Project-URL: Issues, https://github.com/mnesarco/zkeymap/issues
Author-email: Frank Martinez <mnesarco@gmail.com>
License-Expression: MIT
License-File: LICENSE.md
Classifier: Development Status :: 3 - Alpha
Classifier: Intended Audience :: Developers
Classifier: Operating System :: OS Independent
Classifier: Programming Language :: Python :: 3
Requires-Python: >=3.10
Requires-Dist: lark>=1.2.2
Requires-Dist: pyyaml>=6.0.2
Provides-Extra: drawer
Requires-Dist: keymap-drawer>=0.21.0; extra == 'drawer'
